{
  "cliVersion": "5.55.0",
  "generatorName": "fernapi/fern-python-sdk",
  "generatorVersion": "5.14.21",
  "generatorConfig": {
    "package_name": "truefoundry_gateway_sdk",
    "use_request_defaults": "all",
    "pydantic_config": {
      "enum_type": "forward_compatible_python_enums",
      "frozen": false
    },
    "client": {
      "class_name": "BaseTrueFoundryGateway",
      "filename": "base_client.py",
      "exported_class_name": "TrueFoundryGateway",
      "exported_filename": "client.py"
    },
    "pyproject_python_version": ">=3.9",
    "extra_dev_dependencies": {
      "ipython": ">=8.0.0,<10.0.0",
      "Jinja2": ">=3.1.6,<4.0.0",
      "numpydoc": ">=1.7.0,<2.0.0"
    }
  },
  "originGitCommit": "2f62b89ed4136787e1eb2ed11d19831d5533920d",
  "originGitCommitIsDirty": false,
  "invokedBy": "ci",
  "requestedVersion": "0.0.0",
  "ciProvider": "github",
  "sdkVersion": "0.0.0"
}